dbxref/__init__.py
dbxref/config.py
dbxref/main.py
dbxref/providers.yaml
dbxref/resolver.py
dbxref/retriever.py
dbxref/retrieve/__init__.py
dbxref/retrieve/enzyme.py
dbxref/retrieve/gene_ontology.py
dbxref/retrieve/gi.py
dbxref/retrieve/hamap.py
dbxref/retrieve/interpro.py
dbxref/retrieve/kegg.py
dbxref/retrieve/pfam.py
dbxref/retrieve/pubmed.py
dbxref/retrieve/refseq.py
dbxref/retrieve/rfam.py
dbxref/retrieve/sequence_ontology.py
dbxref/retrieve/taxonomy.py
dbxref/retrieve/uniprot.py
dbxref-0.1.7.dist-info/AUTHORS
dbxref-0.1.7.dist-info/LICENSE
dbxref-0.1.7.dist-info/METADATA
dbxref-0.1.7.dist-info/WHEEL
dbxref-0.1.7.dist-info/entry_points.txt
dbxref-0.1.7.dist-info/pbr.json
dbxref-0.1.7.dist-info/top_level.txt
dbxref-0.1.7.dist-info/RECORD
